paramorse/__init__.py
paramorse/__main__.py
paramorse/py.typed
paramorse/core/__init__.py
paramorse/core/config.py
paramorse/core/cover.py
paramorse/core/generator.py
paramorse/core/linguistics.py
paramorse/core/package.py
paramorse/core/payload.py
paramorse/core/transform.py
paramorse/data/words_1k.txt
paramorse/utils/__init__.py
paramorse/utils/helpers.py
paramorse/utils/logging.py
paramorse/utils/paths.py
paramorse/utils/render.py
paramorse-0.1.0.dist-info/METADATA
paramorse-0.1.0.dist-info/WHEEL
paramorse-0.1.0.dist-info/licenses/LICENSE
paramorse-0.1.0.dist-info/RECORD
