Metadata-Version: 2.4
Name: paramorse
Version: 0.1.0
Summary: ParaLinguistic Morse code, a human super language.
Project-URL: Documentation, https://github.com/petertoshev/paramorse#readme
Project-URL: Source, https://github.com/petertoshev/paramorse
Project-URL: Issues, https://github.com/petertoshev/paramorse/issues
Project-URL: Changelog, https://github.com/petertoshev/paramorse/releases
Project-URL: Citation, https://github.com/petertoshev/paramorse/blob/main/CITATION.cff
Author: Peter Toshev
License: MIT License
License-File: LICENSE
Keywords: conlang,linguistics,morse code,paralanguage,superlang
Classifier: Development Status :: 4 - Beta
Classifier: License :: OSI Approved :: MIT License
Classifier: Programming Language :: Python :: 3 :: Only
Classifier: Programming Language :: Python :: 3.10
Classifier: Programming Language :: Python :: 3.11
Classifier: Programming Language :: Python :: 3.12
Classifier: Programming Language :: Python :: 3.13
Classifier: Topic :: Text Processing :: Linguistic
Classifier: Typing :: Typed
Requires-Python: >=3.10
Requires-Dist: spacy>=3.7
Provides-Extra: dev
Requires-Dist: pytest; extra == 'dev'
Requires-Dist: pytest-cov; extra == 'dev'
Requires-Dist: ruff; extra == 'dev'
